{"list":[{"type":"node","id":"0","labels":["Artist"],"properties":{"artistname":"New Order"}},{"type":"node","id":"1","labels":["Artist"],"properties":{"artistname":"Peggy Lee"}},{"type":"node","id":"2","labels":["Artist"],"properties":{"artistname":"The White Stripes"}},{"type":"node","id":"3","labels":["Artist"],"properties":{"artistname":"Woodpecker!"}},{"type":"node","id":"4","labels":["Artist"],"properties":{"artistname":"The Lumineers"}},{"type":"node","id":"5","labels":["Artist"],"properties":{"artistname":"Butthole Surfers"}},{"type":"node","id":"6","labels":["Artist"],"properties":{"artistname":"Cro"}},{"type":"node","id":"7","labels":["Artist"],"properties":{"artistname":"Burzum"}},{"type":"node","id":"8","labels":["Artist"],"properties":{"artistname":"Sunlounger"}},{"type":"node","id":"9","labels":["Artist"],"properties":{"artistname":"Ray Anthony"}},{"type":"node","id":"10","labels":["Artist"],"properties":{"artistname":"ABBA"}},{"type":"node","id":"11","labels":["Artist"],"properties":{"artistname":"B.o.B"}},{"type":"node","id":"12","labels":["Artist"],"properties":{"artistname":"Aretha Franklin"}},{"type":"node","id":"13","labels":["Artist"],"properties":{"artistname":"Faint★Star"}},{"type":"node","id":"14","labels":["Artist"],"properties":{"artistname":"The Goo Goo Dolls"}},{"type":"node","id":"15","labels":["Artist"],"properties":{"artistname":"The Magic Numbers"}},{"type":"node","id":"16","labels":["Artist"],"properties":{"artistname":"Blake Shelton"}},{"type":"node","id":"17","labels":["Artist"],"properties":{"artistname":"Maren Morris"}},{"type":"node","id":"18","labels":["Artist"],"properties":{"artistname":"Billy Paul"}},{"type":"node","id":"19","labels":["Artist"],"properties":{"artistname":"Tye Tribbett"}},{"type":"node","id":"20","labels":["Artist"],"properties":{"artistname":"Ludovico Einaudi"}},{"type":"node","id":"21","labels":["Artist"],"properties":{"artistname":"Europe"}},{"type":"node","id":"22","labels":["Artist"],"properties":{"artistname":"First Aid Kit"}},{"type":"node","id":"23","labels":["Artist"],"properties":{"artistname":"RAT BOY"}},{"type":"node","id":"24","labels":["Artist"],"properties":{"artistname":"Cameo"}},{"type":"node","id":"25","labels":["Artist"],"properties":{"artistname":"Curtis Mayfield"}},{"type":"node","id":"26","labels":["Artist"],"properties":{"artistname":"Wataru Hatano"}},{"type":"node","id":"27","labels":["Artist"],"properties":{"artistname":"Nationalteatern"}},{"type":"node","id":"129","labels":["Artist"],"properties":{"artistname":"Death Cab for Cutie"}},{"type":"node","id":"130","labels":["Artist"],"properties":{"artistname":"Ennio Morricone"}},{"type":"node","id":"131","labels":["Artist"],"properties":{"artistname":"George Strait"}},{"type":"node","id":"132","labels":["Artist"],"properties":{"artistname":"Marky"}},{"type":"node","id":"133","labels":["Artist"],"properties":{"artistname":"Wham!"}},{"type":"node","id":"134","labels":["Artist"],"properties":{"artistname":"omid"}},{"type":"node","id":"135","labels":["Artist"],"properties":{"artistname":"Tokyo Girls' Style"}},{"type":"node","id":"136","labels":["Artist"],"properties":{"artistname":"Style of Eye"}},{"type":"node","id":"137","labels":["Artist"],"properties":{"artistname":"Benedict Kloeckner"}},{"type":"node","id":"138","labels":["Artist"],"properties":{"artistname":"Alborosie"}},{"type":"node","id":"139","labels":["Artist"],"properties":{"artistname":"Papa Roach"}},{"type":"node","id":"140","labels":["Artist"],"properties":{"artistname":"Newfound Road"}},{"type":"node","id":"141","labels":["Artist"],"properties":{"artistname":"Bedlam"}},{"type":"node","id":"142","labels":["Artist"],"properties":{"artistname":"Yiruma"}},{"type":"node","id":"143","labels":["Artist"],"properties":{"artistname":"Udit Narayan"}},{"type":"node","id":"144","labels":["Artist"],"properties":{"artistname":"Anja Schneider"}},{"type":"node","id":"145","labels":["Artist"],"properties":{"artistname":"Behemoth"}},{"type":"node","id":"146","labels":["Artist"],"properties":{"artistname":"The Raconteurs"}},{"type":"node","id":"147","labels":["Artist"],"properties":{"artistname":"A-Lusion"}},{"type":"node","id":"148","labels":["Artist"],"properties":{"artistname":"UVERworld"}},{"type":"node","id":"149","labels":["Artist"],"properties":{"artistname":"Serge Gainsbourg"}},{"type":"node","id":"150","labels":["Artist"],"properties":{"artistname":"Mavado"}},{"type":"node","id":"151","labels":["Artist"],"properties":{"artistname":"D-Block & S-te-Fan"}},{"type":"node","id":"152","labels":["Artist"],"properties":{"artistname":"Chuck Prophet"}},{"type":"node","id":"153","labels":["Artist"],"properties":{"artistname":"Dan Zanes"}},{"type":"node","id":"154","labels":["Artist"],"properties":{"artistname":"Camila Cabello"}},{"type":"node","id":"155","labels":["Artist"],"properties":{"artistname":"B-Front"}},{"type":"node","id":"156","labels":["Artist"],"properties":{"artistname":"Sascha Braemer"}},{"type":"node","id":"157","labels":["Artist"],"properties":{"artistname":"Don McLean"}},{"type":"node","id":"158","labels":["Artist"],"properties":{"artistname":"Tim Maia"}},{"type":"node","id":"159","labels":["Artist"],"properties":{"artistname":"Jon Hopkins"}},{"type":"node","id":"160","labels":["Artist"],"properties":{"artistname":"Ne-Yo"}},{"type":"node","id":"249","labels":["Artist"],"properties":{"artistname":"Game Theory"}},{"type":"node","id":"250","labels":["Artist"],"properties":{"artistname":"Cannibal Corpse"}},{"type":"node","id":"251","labels":["Artist"],"properties":{"artistname":"Jean-Yves Thibaudet"}},{"type":"node","id":"252","labels":["Artist"],"properties":{"artistname":"Queen"}},{"type":"node","id":"253","labels":["Artist"],"properties":{"artistname":"Blake Neely"}},{"type":"node","id":"254","labels":["Artist"],"properties":{"artistname":"Delfeayo Marsalis"}},{"type":"node","id":"255","labels":["Artist"],"properties":{"artistname":"Reso"}},{"type":"node","id":"256","labels":["Artist"],"properties":{"artistname":"Lasse Stefanz"}},{"type":"node","id":"257","labels":["Artist"],"properties":{"artistname":"Alice DJ"}},{"type":"node","id":"258","labels":["Artist"],"properties":{"artistname":"Vienna State Opera Chorus"}},{"type":"node","id":"259","labels":["Artist"],"properties":{"artistname":"System Of A Down"}},{"type":"node","id":"260","labels":["Artist"],"properties":{"artistname":"Awie"}},{"type":"node","id":"261","labels":["Artist"],"properties":{"artistname":"RIZE"}},{"type":"node","id":"262","labels":["Artist"],"properties":{"artistname":"Black Label Society"}},{"type":"node","id":"263","labels":["Artist"],"properties":{"artistname":"The Streets"}},{"type":"node","id":"264","labels":["Artist"],"properties":{"artistname":"KSUKE"}},{"type":"node","id":"265","labels":["Artist"],"properties":{"artistname":"Toneshifterz"}},{"type":"node","id":"266","labels":["Artist"],"properties":{"artistname":"Birdy"}},{"type":"node","id":"267","labels":["Artist"],"properties":{"artistname":"Aziz Ansari"}},{"type":"node","id":"268","labels":["Artist"],"properties":{"artistname":"Cazuza"}},{"type":"node","id":"269","labels":["Artist"],"properties":{"artistname":"Robin Thicke"}},{"type":"node","id":"270","labels":["Artist"],"properties":{"artistname":"João Bosco & Vinicius"}},{"type":"node","id":"271","labels":["Artist"],"properties":{"artistname":"Pakho Chau"}},{"type":"node","id":"272","labels":["Artist"],"properties":{"artistname":"Vybz Kartel"}},{"type":"node","id":"273","labels":["Artist"],"properties":{"artistname":"Danny Elfman"}},{"type":"node","id":"274","labels":["Artist"],"properties":{"artistname":"Noah D"}},{"type":"node","id":"275","labels":["Artist"],"properties":{"artistname":"Natiruts"}},{"type":"node","id":"276","labels":["Artist"],"properties":{"artistname":"Monty"}},{"type":"node","id":"277","labels":["Artist"],"properties":{"artistname":"Average White Band"}},{"type":"node","id":"278","labels":["Artist"],"properties":{"artistname":"Lucy Rose"}},{"type":"node","id":"279","labels":["Artist"],"properties":{"artistname":"Angela Lansbury"}},{"type":"node","id":"280","labels":["Artist"],"properties":{"artistname":"Dreadzone"}},{"type":"node","id":"281","labels":["Artist"],"properties":{"artistname":"Andrew Lloyd Webber"}},{"type":"node","id":"282","labels":["Artist"],"properties":{"artistname":"Juan Magán"}},{"type":"node","id":"283","labels":["Artist"],"properties":{"artistname":"Halil Sezai"}},{"type":"node","id":"284","labels":["Artist"],"properties":{"artistname":"Ron Sexsmith"}},{"type":"node","id":"285","labels":["Artist"],"properties":{"artistname":"Kenny Chesney"}},{"type":"node","id":"286","labels":["Artist"],"properties":{"artistname":"Joshua Radin"}},{"type":"node","id":"287","labels":["Artist"],"properties":{"artistname":"Breaking Benjamin"}},{"type":"node","id":"357","labels":["Artist"],"properties":{"artistname":"The Builders and The Butchers"}},{"type":"node","id":"358","labels":["Artist"],"properties":{"artistname":"Grupo Fundo De Quintal"}},{"type":"node","id":"359","labels":["Artist"],"properties":{"artistname":"The Head and the Heart"}},{"type":"node","id":"360","labels":["Artist"],"properties":{"artistname":"The Creepshow"}},{"type":"node","id":"361","labels":["Artist"],"properties":{"artistname":"Lutan Fyah"}},{"type":"node","id":"362","labels":["Artist"],"properties":{"artistname":"Clinic"}},{"type":"node","id":"363","labels":["Artist"],"properties":{"artistname":"BABYMETAL"}},{"type":"node","id":"364","labels":["Artist"],"properties":{"artistname":"Lil Uzi Vert"}},{"type":"node","id":"365","labels":["Artist"],"properties":{"artistname":"Tasha Baxter"}},{"type":"node","id":"366","labels":["Artist"],"properties":{"artistname":"MAG!C☆PRINCE"}},{"type":"node","id":"367","labels":["Artist"],"properties":{"artistname":"illion"}},{"type":"node","id":"368","labels":["Artist"],"properties":{"artistname":"Orchestral Manoeuvres In The Dark"}},{"type":"node","id":"369","labels":["Artist"],"properties":{"artistname":"Trey Songz"}},{"type":"node","id":"370","labels":["Artist"],"properties":{"artistname":"Chayanne"}},{"type":"node","id":"371","labels":["Artist"],"properties":{"artistname":"John P. Kee"}},{"type":"node","id":"372","labels":["Artist"],"properties":{"artistname":"Urbandub"}},{"type":"node","id":"373","labels":["Artist"],"properties":{"artistname":"Scope DJ"}},{"type":"node","id":"374","labels":["Artist"],"properties":{"artistname":"RYUTist"}},{"type":"node","id":"375","labels":["Artist"],"properties":{"artistname":"Dyland & Lenny"}},{"type":"node","id":"376","labels":["Artist"],"properties":{"artistname":"Lebo M."}},{"type":"node","id":"377","labels":["Artist"],"properties":{"artistname":"Julieta Venegas"}},{"type":"node","id":"378","labels":["Artist"],"properties":{"artistname":"The Black Keys"}},{"type":"node","id":"379","labels":["Artist"],"properties":{"artistname":"Oskar Linnros"}},{"type":"node","id":"380","labels":["Artist"],"properties":{"artistname":"Lamb of God"}},{"type":"node","id":"381","labels":["Artist"],"properties":{"artistname":"Steve Harvey"}},{"type":"node","id":"382","labels":["Artist"],"properties":{"artistname":"Grupo Pagode"}},{"type":"node","id":"383","labels":["Artist"],"properties":{"artistname":"Roupa Nova"}},{"type":"node","id":"384","labels":["Artist"],"properties":{"artistname":"Hudson Mohawke"}},{"type":"node","id":"385","labels":["Artist"],"properties":{"artistname":"La Banda Del Diablo"}},{"type":"node","id":"435","labels":["Artist"],"properties":{"artistname":"Timbalada"}},{"type":"node","id":"436","labels":["Artist"],"properties":{"artistname":"Sarah McLachlan"}},{"type":"node","id":"437","labels":["Artist"],"properties":{"artistname":"Bola"}},{"type":"node","id":"438","labels":["Artist"],"properties":{"artistname":"The Toasters"}},{"type":"node","id":"439","labels":["Artist"],"properties":{"artistname":"Within Temptation"}},{"type":"node","id":"440","labels":["Artist"],"properties":{"artistname":"London Philharmonic Orchestra"}},{"type":"node","id":"441","labels":["Artist"],"properties":{"artistname":"Taylor Swift"}},{"type":"node","id":"442","labels":["Artist"],"properties":{"artistname":"Demi Lovato"}},{"type":"node","id":"443","labels":["Artist"],"properties":{"artistname":"Tim Bendzko"}},{"type":"node","id":"444","labels":["Artist"],"properties":{"artistname":"WEDNESDAY CAMPANELLA"}},{"type":"node","id":"445","labels":["Artist"],"properties":{"artistname":"Necrophagist"}},{"type":"node","id":"446","labels":["Artist"],"properties":{"artistname":"Tove Lo"}},{"type":"node","id":"447","labels":["Artist"],"properties":{"artistname":"Yann Tiersen"}},{"type":"node","id":"448","labels":["Artist"],"properties":{"artistname":"Tower Of Power"}},{"type":"node","id":"449","labels":["Artist"],"properties":{"artistname":"John Lindberg Trio"}},{"type":"node","id":"450","labels":["Artist"],"properties":{"artistname":"Mac"}},{"type":"node","id":"451","labels":["Artist"],"properties":{"artistname":"Lucy Schwartz"}},{"type":"node","id":"452","labels":["Artist"],"properties":{"artistname":"The Tornados"}},{"type":"node","id":"453","labels":["Artist"],"properties":{"artistname":"Monica"}},{"type":"node","id":"454","labels":["Artist"],"properties":{"artistname":"Paolo Nutini"}},{"type":"node","id":"455","labels":["Artist"],"properties":{"artistname":"Eric Martin"}},{"type":"node","id":"456","labels":["Artist"],"properties":{"artistname":"St. Lucia"}},{"type":"node","id":"457","labels":["Artist"],"properties":{"artistname":"Pearl Jam"}},{"type":"node","id":"458","labels":["Artist"],"properties":{"artistname":"Max Richter"}},{"type":"node","id":"459","labels":["Artist"],"properties":{"artistname":"Hippie Sabotage"}},{"type":"node","id":"460","labels":["Artist"],"properties":{"artistname":"Feed Me"}},{"type":"node","id":"461","labels":["Artist"],"properties":{"artistname":"Sam Smith"}},{"type":"node","id":"462","labels":["Artist"],"properties":{"artistname":"Adele"}},{"type":"node","id":"463","labels":["Artist"],"properties":{"artistname":"Orchestra Sinfonica di Milano Giuseppe Verdi"}},{"type":"node","id":"464","labels":["Artist"],"properties":{"artistname":"Plaid"}},{"type":"node","id":"465","labels":["Artist"],"properties":{"artistname":"Dubstep Mafia"}},{"type":"node","id":"466","labels":["Artist"],"properties":{"artistname":"Péter Nagy"}},{"type":"node","id":"467","labels":["Artist"],"properties":{"artistname":"Vicentico"}},{"type":"node","id":"468","labels":["Artist"],"properties":{"artistname":"Florence + The Machine"}},{"type":"node","id":"525","labels":["Artist"],"properties":{"artistname":"Bronski Beat"}},{"type":"node","id":"526","labels":["Artist"],"properties":{"artistname":"Christina Perri"}},{"type":"node","id":"527","labels":["Artist"],"properties":{"artistname":"Jorge Ortiz"}},{"type":"node","id":"528","labels":["Artist"],"properties":{"artistname":"DE DE MOUSE"}},{"type":"node","id":"529","labels":["Artist"],"properties":{"artistname":"PARTYNEXTDOOR"}},{"type":"node","id":"530","labels":["Artist"],"properties":{"artistname":"Yida Huang"}},{"type":"node","id":"531","labels":["Artist"],"properties":{"artistname":"Pendulum"}},{"type":"node","id":"532","labels":["Artist"],"properties":{"artistname":"Grimes"}},{"type":"node","id":"533","labels":["Artist"],"properties":{"artistname":"Post Malone"}},{"type":"node","id":"534","labels":["Artist"],"properties":{"artistname":"Hellrazor"}},{"type":"node","id":"535","labels":["Artist"],"properties":{"artistname":"Matthew Sweet"}},{"type":"node","id":"536","labels":["Artist"],"properties":{"artistname":"AIRBAG"}},{"type":"node","id":"537","labels":["Artist"],"properties":{"artistname":"Whigfield"}},{"type":"node","id":"538","labels":["Artist"],"properties":{"artistname":"Stephan Bodzin"}},{"type":"node","id":"539","labels":["Artist"],"properties":{"artistname":"John Williams"}},{"type":"node","id":"540","labels":["Artist"],"properties":{"artistname":"Croma Latina"}},{"type":"node","id":"541","labels":["Artist"],"properties":{"artistname":"Sa Dingding"}},{"type":"node","id":"542","labels":["Artist"],"properties":{"artistname":"Munich Radio Orchestra"}},{"type":"node","id":"543","labels":["Artist"],"properties":{"artistname":"Banda Garota Safada"}},{"type":"node","id":"544","labels":["Artist"],"properties":{"artistname":"Decapitated"}},{"type":"node","id":"545","labels":["Artist"],"properties":{"artistname":"Crooked Still"}},{"type":"node","id":"546","labels":["Artist"],"properties":{"artistname":"A$AP Rocky"}},{"type":"node","id":"547","labels":["Artist"],"properties":{"artistname":"Juicy J"}},{"type":"node","id":"548","labels":["Artist"],"properties":{"artistname":"Wayne Shorter"}},{"type":"node","id":"549","labels":["Artist"],"properties":{"artistname":"Che'Nelle"}},{"type":"node","id":"550","labels":["Artist"],"properties":{"artistname":"Bossacucanova"}},{"type":"node","id":"551","labels":["Artist"],"properties":{"artistname":"Flume"}},{"type":"node","id":"552","labels":["Artist"],"properties":{"artistname":"New York Philharmonic"}},{"type":"node","id":"553","labels":["Artist"],"properties":{"artistname":"Night Beats"}},{"type":"node","id":"605","labels":["Artist"],"properties":{"artistname":"Silverstein"}},{"type":"node","id":"606","labels":["Artist"],"properties":{"artistname":"Mohombi"}},{"type":"node","id":"607","labels":["Artist"],"properties":{"artistname":"The Devil Wears Prada"}},{"type":"node","id":"608","labels":["Artist"],"properties":{"artistname":"Signum"}},{"type":"node","id":"609","labels":["Artist"],"properties":{"artistname":"Randy Houser"}},{"type":"node","id":"610","labels":["Artist"],"properties":{"artistname":"Datuk Ahmad Jais"}},{"type":"node","id":"611","labels":["Artist"],"properties":{"artistname":"脫拉庫"}},{"type":"node","id":"612","labels":["Artist"],"properties":{"artistname":"Journey"}},{"type":"node","id":"613","labels":["Artist"],"properties":{"artistname":"Kenny Loggins"}},{"type":"node","id":"614","labels":["Artist"],"properties":{"artistname":"Derrick May"}},{"type":"node","id":"615","labels":["Artist"],"properties":{"artistname":"Papa Grows Funk"}},{"type":"node","id":"616","labels":["Artist"],"properties":{"artistname":"Sarah Geronimo"}},{"type":"node","id":"617","labels":["Artist"],"properties":{"artistname":"Theo Croker"}},{"type":"node","id":"618","labels":["Artist"],"properties":{"artistname":"Cecil Payne"}},{"type":"node","id":"619","labels":["Artist"],"properties":{"artistname":"Dani Black"}},{"type":"node","id":"620","labels":["Artist"],"properties":{"artistname":"Satyricon"}},{"type":"node","id":"621","labels":["Artist"],"properties":{"artistname":"Jerry Goldsmith"}},{"type":"node","id":"622","labels":["Artist"],"properties":{"artistname":"Zeds Dead"}},{"type":"node","id":"623","labels":["Artist"],"properties":{"artistname":"Pale Seas"}},{"type":"node","id":"624","labels":["Artist"],"properties":{"artistname":"El Cata"}},{"type":"node","id":"625","labels":["Artist"],"properties":{"artistname":"Dash Berlin"}},{"type":"node","id":"626","labels":["Artist"],"properties":{"artistname":"Buffalo Tom"}},{"type":"node","id":"627","labels":["Artist"],"properties":{"artistname":"Puan Sri Saloma"}},{"type":"node","id":"628","labels":["Artist"],"properties":{"artistname":"Montgomery Gentry"}},{"type":"node","id":"629","labels":["Artist"],"properties":{"artistname":"Edwin Luna y La Trakalosa de Monterrey"}},{"type":"node","id":"630","labels":["Artist"],"properties":{"artistname":"Randy Newman"}},{"type":"node","id":"631","labels":["Artist"],"properties":{"artistname":"Engenheiros Do Hawaii"}},{"type":"node","id":"632","labels":["Artist"],"properties":{"artistname":"Rotten Sound"}},{"type":"node","id":"633","labels":["Artist"],"properties":{"artistname":"Matthew Koma"}},{"type":"node","id":"634","labels":["Artist"],"properties":{"artistname":"Lucenzo"}},{"type":"node","id":"635","labels":["Artist"],"properties":{"artistname":"Baby Rasta & Gringo"}},{"type":"node","id":"636","labels":["Artist"],"properties":{"artistname":"Diana Ross & The Supremes"}},{"type":"node","id":"637","labels":["Artist"],"properties":{"artistname":"The Crystal Method"}},{"type":"node","id":"638","labels":["Artist"],"properties":{"artistname":"Jessica Andrews"}},{"type":"node","id":"639","labels":["Artist"],"properties":{"artistname":"Helene Schneiderman"}},{"type":"node","id":"640","labels":["Artist"],"properties":{"artistname":"Denise Ho"}},{"type":"node","id":"688","labels":["Artist"],"properties":{"artistname":"童安格"}},{"type":"node","id":"689","labels":["Artist"],"properties":{"artistname":"Mountain"}},{"type":"node","id":"690","labels":["Artist"],"properties":{"artistname":"Joey Albert"}},{"type":"node","id":"691","labels":["Artist"],"properties":{"artistname":"A Boogie Wit da Hoodie"}},{"type":"node","id":"692","labels":["Artist"],"properties":{"artistname":"Sonny Rollins"}},{"type":"node","id":"693","labels":["Artist"],"properties":{"artistname":"TOTO"}},{"type":"node","id":"694","labels":["Artist"],"properties":{"artistname":"Alexi Murdoch"}},{"type":"node","id":"695","labels":["Artist"],"properties":{"artistname":"João Donato"}},{"type":"node","id":"696","labels":["Artist"],"properties":{"artistname":"Iain Sutherland"}},{"type":"node","id":"697","labels":["Artist"],"properties":{"artistname":"Toumani Diabaté"}},{"type":"node","id":"698","labels":["Artist"],"properties":{"artistname":"Trivium"}},{"type":"node","id":"699","labels":["Artist"],"properties":{"artistname":"Brigitte Bardot"}},{"type":"node","id":"700","labels":["Artist"],"properties":{"artistname":"LCD Soundsystem"}},{"type":"node","id":"701","labels":["Artist"],"properties":{"artistname":"Sesto Bruscantini"}},{"type":"node","id":"702","labels":["Artist"],"properties":{"artistname":"Mount Kimbie"}},{"type":"node","id":"703","labels":["Artist"],"properties":{"artistname":"Children Of Bodom"}},{"type":"node","id":"704","labels":["Artist"],"properties":{"artistname":"The Growlers"}},{"type":"node","id":"705","labels":["Artist"],"properties":{"artistname":"K. Michelle"}},{"type":"node","id":"706","labels":["Artist"],"properties":{"artistname":"Chris James"}},{"type":"node","id":"707","labels":["Artist"],"properties":{"artistname":"Rolf Løvland"}},{"type":"node","id":"708","labels":["Artist"],"properties":{"artistname":"Victor & Leo"}},{"type":"node","id":"709","labels":["Artist"],"properties":{"artistname":"Bat For Lashes"}},{"type":"node","id":"710","labels":["Artist"],"properties":{"artistname":"Anitta"}},{"type":"node","id":"711","labels":["Artist"],"properties":{"artistname":"Attack Attack!"}},{"type":"node","id":"745","labels":["Artist"],"properties":{"artistname":"Teencats"}},{"type":"node","id":"746","labels":["Artist"],"properties":{"artistname":"RAI Symphony Orchestra & Chorus of Rome"}},{"type":"node","id":"747","labels":["Artist"],"properties":{"artistname":"K. S. Chithra"}},{"type":"node","id":"748","labels":["Artist"],"properties":{"artistname":"Marcus Belgrave"}},{"type":"node","id":"749","labels":["Artist"],"properties":{"artistname":"Lykke Li"}},{"type":"node","id":"754","labels":["Artist"],"properties":{"artistname":"Rancid"}},{"type":"node","id":"755","labels":["Artist"],"properties":{"artistname":"Meek Mill"}},{"type":"node","id":"756","labels":["Artist"],"properties":{"artistname":"Pinch"}},{"type":"node","id":"757","labels":["Artist"],"properties":{"artistname":"Carl Craig"}},{"type":"node","id":"758","labels":["Artist"],"properties":{"artistname":"RDX"}},{"type":"node","id":"759","labels":["Artist"],"properties":{"artistname":"In This Moment"}},{"type":"node","id":"760","labels":["Artist"],"properties":{"artistname":"Robyn"}},{"type":"node","id":"761","labels":["Artist"],"properties":{"artistname":"Enrique Iglesias"}},{"type":"node","id":"762","labels":["Artist"],"properties":{"artistname":"Ratatat"}},{"type":"node","id":"763","labels":["Artist"],"properties":{"artistname":"Jónsi"}},{"type":"node","id":"764","labels":["Artist"],"properties":{"artistname":"Adnan Sami"}},{"type":"node","id":"765","labels":["Artist"],"properties":{"artistname":"Arch Enemy"}},{"type":"node","id":"766","labels":["Artist"],"properties":{"artistname":"We Came As Romans"}},{"type":"node","id":"767","labels":["Artist"],"properties":{"artistname":"Cristiano Araújo"}},{"type":"node","id":"768","labels":["Artist"],"properties":{"artistname":"Gunnar Stiller"}},{"type":"node","id":"769","labels":["Artist"],"properties":{"artistname":"Smokie Norful"}},{"type":"node","id":"770","labels":["Artist"],"properties":{"artistname":"Sia"}},{"type":"node","id":"771","labels":["Artist"],"properties":{"artistname":"Autechre"}},{"type":"node","id":"772","labels":["Artist"],"properties":{"artistname":"The Fleshtones"}},{"type":"node","id":"773","labels":["Artist"],"properties":{"artistname":"Basshunter"}},{"type":"node","id":"774","labels":["Artist"],"properties":{"artistname":"lecca"}},{"type":"node","id":"775","labels":["Artist"],"properties":{"artistname":"Daddy Yankee"}},{"type":"node","id":"776","labels":["Artist"],"properties":{"artistname":"Lillias White"}},{"type":"node","id":"777","labels":["Artist"],"properties":{"artistname":"Camila"}},{"type":"node","id":"778","labels":["Artist"],"properties":{"artistname":"BoM"}},{"type":"node","id":"779","labels":["Artist"],"properties":{"artistname":"P!nk"}},{"type":"node","id":"780","labels":["Artist"],"properties":{"artistname":"Example"}},{"type":"node","id":"781","labels":["Artist"],"properties":{"artistname":"Sorriso Maroto"}},{"type":"node","id":"811","labels":["Artist"],"properties":{"artistname":"Germs"}},{"type":"node","id":"812","labels":["Artist"],"properties":{"artistname":"Meghan Trainor"}},{"type":"node","id":"813","labels":["Artist"],"properties":{"artistname":"Yandel"}},{"type":"node","id":"814","labels":["Artist"],"properties":{"artistname":"808 State"}},{"type":"node","id":"815","labels":["Artist"],"properties":{"artistname":"Screamin' Jay Hawkins"}},{"type":"node","id":"816","labels":["Artist"],"properties":{"artistname":"Alma Mahler"}},{"type":"node","id":"817","labels":["Artist"],"properties":{"artistname":"Beck"}},{"type":"node","id":"818","labels":["Artist"],"properties":{"artistname":"Maurice Joshua"}},{"type":"node","id":"819","labels":["Artist"],"properties":{"artistname":"Anonymous"}},{"type":"node","id":"820","labels":["Artist"],"properties":{"artistname":"Raju Singh"}},{"type":"node","id":"821","labels":["Artist"],"properties":{"artistname":"Rick James"}},{"type":"node","id":"822","labels":["Artist"],"properties":{"artistname":"Maria Bamford"}},{"type":"node","id":"823","labels":["Artist"],"properties":{"artistname":"Romeo Santos"}},{"type":"node","id":"824","labels":["Artist"],"properties":{"artistname":"Silver Sun"}},{"type":"node","id":"825","labels":["Artist"],"properties":{"artistname":"Kehlani"}},{"type":"node","id":"826","labels":["Artist"],"properties":{"artistname":"The Orchestra National De La Radiodiffusion Francaise"}},{"type":"node","id":"827","labels":["Artist"],"properties":{"artistname":"Logic"}},{"type":"node","id":"828","labels":["Artist"],"properties":{"artistname":"Pritam"}},{"type":"node","id":"829","labels":["Artist"],"properties":{"artistname":"Clan of Xymox"}},{"type":"node","id":"830","labels":["Artist"],"properties":{"artistname":"Justin Martin"}},{"type":"node","id":"831","labels":["Artist"],"properties":{"artistname":"Christoph Willibald Gluck"}},{"type":"node","id":"832","labels":["Artist"],"properties":{"artistname":"Ralphi Rosario"}},{"type":"node","id":"833","labels":["Artist"],"properties":{"artistname":"Chris Lake"}},{"type":"node","id":"834","labels":["Artist"],"properties":{"artistname":"Major Lazer"}},{"type":"node","id":"835","labels":["Artist"],"properties":{"artistname":"La-33"}},{"type":"node","id":"836","labels":["Artist"],"properties":{"artistname":"MINMI"}},{"type":"node","id":"837","labels":["Artist"],"properties":{"artistname":"Take"}},{"type":"node","id":"838","labels":["Artist"],"properties":{"artistname":"Pascal Obispo"}},{"type":"node","id":"839","labels":["Artist"],"properties":{"artistname":"Seether"}},{"type":"node","id":"840","labels":["Artist"],"properties":{"artistname":"Punch Brothers"}},{"type":"node","id":"841","labels":["Artist"],"properties":{"artistname":"Valen Hsu"}},{"type":"node","id":"882","labels":["Artist"],"properties":{"artistname":"Johnny Winter"}},{"type":"node","id":"883","labels":["Artist"],"properties":{"artistname":"Seinabo Sey"}},{"type":"node","id":"884","labels":["Artist"],"properties":{"artistname":"Demet Akalın"}},{"type":"node","id":"885","labels":["Artist"],"properties":{"artistname":"Drake"}},{"type":"node","id":"886","labels":["Artist"],"properties":{"artistname":"Mohsen Namjoo"}},{"type":"node","id":"887","labels":["Artist"],"properties":{"artistname":"Bezerra Da Silva"}},{"type":"node","id":"888","labels":["Artist"],"properties":{"artistname":"Eric Church"}},{"type":"node","id":"889","labels":["Artist"],"properties":{"artistname":"Lil' Kim"}},{"type":"node","id":"890","labels":["Artist"],"properties":{"artistname":"Vent"}},{"type":"node","id":"891","labels":["Artist"],"properties":{"artistname":"Gareth Emery"}},{"type":"node","id":"892","labels":["Artist"],"properties":{"artistname":"London Grammar"}},{"type":"node","id":"893","labels":["Artist"],"properties":{"artistname":"Blutengel"}},{"type":"node","id":"894","labels":["Artist"],"properties":{"artistname":"Avicii"}},{"type":"node","id":"895","labels":["Artist"],"properties":{"artistname":"In Flames"}},{"type":"node","id":"896","labels":["Artist"],"properties":{"artistname":"Jatin-Lalit"}},{"type":"node","id":"897","labels":["Artist"],"properties":{"artistname":"Stone Temple Pilots"}},{"type":"node","id":"898","labels":["Artist"],"properties":{"artistname":"Amadou & Mariam"}},{"type":"node","id":"899","labels":["Artist"],"properties":{"artistname":"Tata Vega"}},{"type":"node","id":"900","labels":["Artist"],"properties":{"artistname":"A-Mei Chang"}},{"type":"node","id":"901","labels":["Artist"],"properties":{"artistname":"Big Pun"}},{"type":"node","id":"902","labels":["Artist"],"properties":{"artistname":"The Tri-City Singers"}},{"type":"node","id":"903","labels":["Artist"],"properties":{"artistname":"Banda El Recodo"}},{"type":"node","id":"904","labels":["Artist"],"properties":{"artistname":"Ms. Lauryn Hill"}},{"type":"node","id":"905","labels":["Artist"],"properties":{"artistname":"Mathias"}},{"type":"node","id":"906","labels":["Artist"],"properties":{"artistname":"August Burns Red"}},{"type":"node","id":"907","labels":["Artist"],"properties":{"artistname":"D-Block"}},{"type":"node","id":"908","labels":["Artist"],"properties":{"artistname":"A Great Big World"}},{"type":"node","id":"938","labels":["Artist"],"properties":{"artistname":"Tyler Farr"}},{"type":"node","id":"939","labels":["Artist"],"properties":{"artistname":"Renée Zellweger"}},{"type":"node","id":"940","labels":["Artist"],"properties":{"artistname":"Olly Murs"}},{"type":"node","id":"941","labels":["Artist"],"properties":{"artistname":"Alligatoah"}},{"type":"node","id":"942","labels":["Artist"],"properties":{"artistname":"Yalın"}},{"type":"node","id":"943","labels":["Artist"],"properties":{"artistname":"Tinashe"}},{"type":"node","id":"944","labels":["Artist"],"properties":{"artistname":"The Bossa Nova All Stars"}},{"type":"node","id":"945","labels":["Artist"],"properties":{"artistname":"Excision"}},{"type":"node","id":"946","labels":["Artist"],"properties":{"artistname":"Lana Del Rey"}},{"type":"node","id":"947","labels":["Artist"],"properties":{"artistname":"Janelle Monáe"}},{"type":"node","id":"948","labels":["Artist"],"properties":{"artistname":"Louise Attaque"}},{"type":"node","id":"949","labels":["Artist"],"properties":{"artistname":"Shem"}},{"type":"node","id":"950","labels":["Artist"],"properties":{"artistname":"Pedro Laurenz"}},{"type":"node","id":"951","labels":["Artist"],"properties":{"artistname":"Junior Kelly"}},{"type":"node","id":"952","labels":["Artist"],"properties":{"artistname":"Étienne de Crécy"}},{"type":"node","id":"953","labels":["Artist"],"properties":{"artistname":"Chrystian & Ralf"}},{"type":"node","id":"954","labels":["Artist"],"properties":{"artistname":"Queen Latifah"}},{"type":"node","id":"955","labels":["Artist"],"properties":{"artistname":"Mitch Crown"}},{"type":"node","id":"956","labels":["Artist"],"properties":{"artistname":"Kieran Hebden"}},{"type":"node","id":"957","labels":["Artist"],"properties":{"artistname":"Zedd"}},{"type":"node","id":"958","labels":["Artist"],"properties":{"artistname":"Roberta Miranda"}},{"type":"node","id":"959","labels":["Artist"],"properties":{"artistname":"Caribou"}},{"type":"node","id":"960","labels":["Artist"],"properties":{"artistname":"Ty Dolla $ign"}},{"type":"node","id":"961","labels":["Artist"],"properties":{"artistname":"Mr. Fingers"}},{"type":"node","id":"962","labels":["Artist"],"properties":{"artistname":"Emílio Santiago"}},{"type":"node","id":"963","labels":["Artist"],"properties":{"artistname":"VNV Nation"}},{"type":"node","id":"964","labels":["Artist"],"properties":{"artistname":"Les Misérables - Original London Cast"}},{"type":"node","id":"965","labels":["Artist"],"properties":{"artistname":"Astrolites"}},{"type":"node","id":"966","labels":["Artist"],"properties":{"artistname":"Tiffany Alvord"}},{"type":"node","id":"986","labels":["Artist"],"properties":{"artistname":"Aerosmith"}},{"type":"node","id":"987","labels":["Artist"],"properties":{"artistname":"The Selecter"}},{"type":"node","id":"988","labels":["Artist"],"properties":{"artistname":"Queens of the Stone Age"}},{"type":"node","id":"989","labels":["Artist"],"properties":{"artistname":"Édith Piaf"}},{"type":"node","id":"990","labels":["Artist"],"properties":{"artistname":"ATB"}},{"type":"node","id":"991","labels":["Artist"],"properties":{"artistname":"Yves Montand"}},{"type":"node","id":"992","labels":["Artist"],"properties":{"artistname":"Wisin"}},{"type":"node","id":"993","labels":["Artist"],"properties":{"artistname":"Arlindo Cruz"}},{"type":"node","id":"994","labels":["Artist"],"properties":{"artistname":"Charlie Brown Jr."}},{"type":"node","id":"995","labels":["Artist"],"properties":{"artistname":"GD & TOP"}},{"type":"node","id":"996","labels":["Artist"],"properties":{"artistname":"Agoraphobic Nosebleed"}},{"type":"node","id":"997","labels":["Artist"],"properties":{"artistname":"The Mighty Mighty Bosstones"}},{"type":"node","id":"998","labels":["Artist"],"properties":{"artistname":"Christophe Beck"}},{"type":"node","id":"1014","labels":["Artist"],"properties":{"artistname":"SEBASTIAN X"}},{"type":"node","id":"1015","labels":["Artist"],"properties":{"artistname":"Pixote"}},{"type":"node","id":"1016","labels":["Artist"],"properties":{"artistname":"Kierra Sheard"}},{"type":"node","id":"1017","labels":["Artist"],"properties":{"artistname":"Fall Out Boy"}},{"type":"node","id":"1018","labels":["Artist"],"properties":{"artistname":"Emperor"}},{"type":"node","id":"1019","labels":["Artist"],"properties":{"artistname":"İbrahim Tatlıses"}},{"type":"node","id":"1020","labels":["Artist"],"properties":{"artistname":"Das Karussell"}},{"type":"node","id":"1021","labels":["Artist"],"properties":{"artistname":"Zezé Di Camargo & Luciano"}},{"type":"node","id":"1022","labels":["Artist"],"properties":{"artistname":"ill.gates"}},{"type":"node","id":"1023","labels":["Artist"],"properties":{"artistname":"Nari"}},{"type":"node","id":"1024","labels":["Artist"],"properties":{"artistname":"Young Thug"}},{"type":"node","id":"1025","labels":["Artist"],"properties":{"artistname":"Marvin Gaye"}},{"type":"node","id":"1026","labels":["Artist"],"properties":{"artistname":"Kendrick Lamar"}},{"type":"node","id":"1027","labels":["Artist"],"properties":{"artistname":"Felix Mendelssohn"}},{"type":"node","id":"1028","labels":["Artist"],"properties":{"artistname":"Pat Boone"}},{"type":"node","id":"1029","labels":["Artist"],"properties":{"artistname":"Byron Cage"}},{"type":"node","id":"1030","labels":["Artist"],"properties":{"artistname":"Alien Sex Fiend"}},{"type":"node","id":"1031","labels":["Artist"],"properties":{"artistname":"Igor Stravinsky"}},{"type":"node","id":"1032","labels":["Artist"],"properties":{"artistname":"Massive Attack"}},{"type":"node","id":"1033","labels":["Artist"],"properties":{"artistname":"DJ Fresh"}},{"type":"node","id":"1034","labels":["Artist"],"properties":{"artistname":"The Brian Jonestown Massacre"}},{"type":"node","id":"1035","labels":["Artist"],"properties":{"artistname":"Broadside"}},{"type":"node","id":"1036","labels":["Artist"],"properties":{"artistname":"Steve Moakler"}},{"type":"node","id":"1037","labels":["Artist"],"properties":{"artistname":"Rascal Flatts"}},{"type":"node","id":"1038","labels":["Artist"],"properties":{"artistname":"Ivy Lab"}},{"type":"node","id":"1039","labels":["Artist"],"properties":{"artistname":"Marc Anthony"}},{"type":"node","id":"1040","labels":["Artist"],"properties":{"artistname":"Wisin & Yandel"}},{"type":"node","id":"1041","labels":["Artist"],"properties":{"artistname":"Ellie Goulding"}},{"type":"node","id":"1042","labels":["Artist"],"properties":{"artistname":"Gary Gulman"}},{"type":"node","id":"1043","labels":["Artist"],"properties":{"artistname":"Attila"}},{"type":"node","id":"1044","labels":["Artist"],"properties":{"artistname":"Michael Hedges"}},{"type":"node","id":"1045","labels":["Artist"],"properties":{"artistname":"Nate Ruess"}},{"type":"node","id":"1046","labels":["Artist"],"properties":{"artistname":"Kesha"}},{"type":"node","id":"1047","labels":["Artist"],"properties":{"artistname":"Ritchie Valens"}},{"type":"node","id":"1071","labels":["Artist"],"properties":{"artistname":"MJ Cole"}},{"type":"node","id":"1072","labels":["Artist"],"properties":{"artistname":"John Barry"}},{"type":"node","id":"1073","labels":["Artist"],"properties":{"artistname":"Vishal-Shekhar"}},{"type":"node","id":"1074","labels":["Artist"],"properties":{"artistname":"Gorillaz"}},{"type":"node","id":"1075","labels":["Artist"],"properties":{"artistname":"Casa De Leones"}},{"type":"node","id":"1076","labels":["Artist"],"properties":{"artistname":"Campanella"}},{"type":"node","id":"1077","labels":["Artist"],"properties":{"artistname":"Tyga"}},{"type":"node","id":"1078","labels":["Artist"],"properties":{"artistname":"Zé Ramalho"}},{"type":"node","id":"1079","labels":["Artist"],"properties":{"artistname":"Minami Takahashi"}},{"type":"node","id":"1080","labels":["Artist"],"properties":{"artistname":"Ruben Gazarian"}},{"type":"node","id":"1081","labels":["Artist"],"properties":{"artistname":"Ebi"}},{"type":"node","id":"1082","labels":["Artist"],"properties":{"artistname":"Ferry Corsten"}},{"type":"node","id":"1083","labels":["Artist"],"properties":{"artistname":"FlowBack"}},{"type":"node","id":"1084","labels":["Artist"],"properties":{"artistname":"Sylvan Esso"}},{"type":"node","id":"1085","labels":["Artist"],"properties":{"artistname":"Danny Byrd"}},{"type":"node","id":"1086","labels":["Artist"],"properties":{"artistname":"Metallica"}},{"type":"node","id":"1087","labels":["Artist"],"properties":{"artistname":"Kristin Chenoweth"}},{"type":"node","id":"1088","labels":["Artist"],"properties":{"artistname":"Jamie xx"}},{"type":"node","id":"1089","labels":["Artist"],"properties":{"artistname":"Seu Jorge"}},{"type":"node","id":"1090","labels":["Artist"],"properties":{"artistname":"Cat Power"}},{"type":"node","id":"1091","labels":["Artist"],"properties":{"artistname":"Gilberto Santa Rosa"}},{"type":"node","id":"1092","labels":["Artist"],"properties":{"artistname":"LeAnn Rimes"}},{"type":"node","id":"1093","labels":["Artist"],"properties":{"artistname":"LinQ"}},{"type":"node","id":"1094","labels":["Artist"],"properties":{"artistname":"Dimitri Vegas & Like Mike"}},{"type":"node","id":"1095","labels":["Artist"],"properties":{"artistname":"Gustavo Lins"}},{"type":"node","id":"1096","labels":["Artist"],"properties":{"artistname":"Paige O'Hara"}},{"type":"node","id":"1097","labels":["Artist"],"properties":{"artistname":"Charli XCX"}},{"type":"node","id":"1098","labels":["Artist"],"properties":{"artistname":"Sublime"}},{"type":"node","id":"1099","labels":["Artist"],"properties":{"artistname":"Tujamo"}},{"type":"node","id":"1100","labels":["Artist"],"properties":{"artistname":"Los Angeles Philharmonic"}},{"type":"node","id":"1101","labels":["Artist"],"properties":{"artistname":"Marshmello"}},{"type":"node","id":"1102","labels":["Artist"],"properties":{"artistname":"The Brian Setzer Orchestra"}},{"type":"node","id":"1103","labels":["Artist"],"properties":{"artistname":"Tia Carrere"}},{"type":"node","id":"1104","labels":["Artist"],"properties":{"artistname":"The Roots"}},{"type":"node","id":"1120","labels":["Artist"],"properties":{"artistname":"Aril Brikha"}},{"type":"node","id":"1121","labels":["Artist"],"properties":{"artistname":"Nirvana"}},{"type":"node","id":"1122","labels":["Artist"],"properties":{"artistname":"Sonu Nigam"}},{"type":"node","id":"1123","labels":["Artist"],"properties":{"artistname":"NAV"}},{"type":"node","id":"1124","labels":["Artist"],"properties":{"artistname":"Cesária Evora"}},{"type":"node","id":"1125","labels":["Artist"],"properties":{"artistname":"Ibrahim Maalouf"}},{"type":"node","id":"1126","labels":["Artist"],"properties":{"artistname":"Afrojack"}},{"type":"node","id":"1127","labels":["Artist"],"properties":{"artistname":"John Mellencamp"}},{"type":"node","id":"1128","labels":["Artist"],"properties":{"artistname":"Sara Bareilles"}},{"type":"node","id":"1129","labels":["Artist"],"properties":{"artistname":"Dido"}},{"type":"node","id":"1130","labels":["Artist"],"properties":{"artistname":"Galantis"}},{"type":"node","id":"1131","labels":["Artist"],"properties":{"artistname":"Edgar Meyer"}},{"type":"node","id":"1132","labels":["Artist"],"properties":{"artistname":"The Chainsmokers"}},{"type":"node","id":"1133","labels":["Artist"],"properties":{"artistname":"Paul Gay"}},{"type":"node","id":"1134","labels":["Artist"],"properties":{"artistname":"Perdidos De Sinaloa"}},{"type":"node","id":"1135","labels":["Artist"],"properties":{"artistname":"Kraftwerk"}},{"type":"node","id":"1136","labels":["Artist"],"properties":{"artistname":"Walter Egan"}},{"type":"node","id":"1137","labels":["Artist"],"properties":{"artistname":"Camille Saint-Saëns"}},{"type":"node","id":"1138","labels":["Artist"],"properties":{"artistname":"Thrice"}},{"type":"node","id":"1139","labels":["Artist"],"properties":{"artistname":"The Cinematic Orchestra"}},{"type":"node","id":"1140","labels":["Artist"],"properties":{"artistname":"Kru"}},{"type":"node","id":"1141","labels":["Artist"],"properties":{"artistname":"David Parry"}},{"type":"node","id":"1142","labels":["Artist"],"properties":{"artistname":"Marshanda"}},{"type":"node","id":"1143","labels":["Artist"],"properties":{"artistname":"The Amazons"}},{"type":"node","id":"1144","labels":["Artist"],"properties":{"artistname":"The Piano Guys"}},{"type":"node","id":"1145","labels":["Artist"],"properties":{"artistname":"The Laurie Berkner Band"}},{"type":"node","id":"1146","labels":["Artist"],"properties":{"artistname":"Coone"}},{"type":"node","id":"1147","labels":["Artist"],"properties":{"artistname":"Sena Jurinac"}},{"type":"node","id":"1148","labels":["Artist"],"properties":{"artistname":"Pixies"}},{"type":"node","id":"1149","labels":["Artist"],"properties":{"artistname":"Ivan Lins"}},{"type":"node","id":"1150","labels":["Artist"],"properties":{"artistname":"Tommy Dorsey"}},{"type":"node","id":"1172","labels":["Artist"],"properties":{"artistname":"Steve Jablonsky"}},{"type":"node","id":"1173","labels":["Artist"],"properties":{"artistname":"Amy Winehouse"}},{"type":"node","id":"1174","labels":["Artist"],"properties":{"artistname":"Katy Perry"}},{"type":"node","id":"1175","labels":["Artist"],"properties":{"artistname":"Victoria Beckham"}},{"type":"node","id":"1176","labels":["Artist"],"properties":{"artistname":"Neck Deep"}},{"type":"node","id":"1177","labels":["Artist"],"properties":{"artistname":"Pharrell Williams"}},{"type":"node","id":"1178","labels":["Artist"],"properties":{"artistname":"Hardwell"}},{"type":"node","id":"1179","labels":["Artist"],"properties":{"artistname":"Mirella Freni"}},{"type":"node","id":"1180","labels":["Artist"],"properties":{"artistname":"Old Crow Medicine Show"}},{"type":"node","id":"1181","labels":["Artist"],"properties":{"artistname":"Zapp"}},{"type":"node","id":"1182","labels":["Artist"],"properties":{"artistname":"The Impressions"}},{"type":"node","id":"1183","labels":["Artist"],"properties":{"artistname":"I Wayne"}},{"type":"node","id":"1184","labels":["Artist"],"properties":{"artistname":"Heist"}},{"type":"node","id":"1185","labels":["Artist"],"properties":{"artistname":"Fetty Wap"}},{"type":"node","id":"1186","labels":["Artist"],"properties":{"artistname":"Lightnin' Hopkins"}},{"type":"node","id":"1187","labels":["Artist"],"properties":{"artistname":"Chain Reaction"}},{"type":"node","id":"1188","labels":["Artist"],"properties":{"artistname":"Moraes Moreira"}},{"type":"node","id":"1189","labels":["Artist"],"properties":{"artistname":"Kareena Kapoor"}},{"type":"node","id":"1190","labels":["Artist"],"properties":{"artistname":"Joan Manuel Serrat"}},{"type":"node","id":"1191","labels":["Artist"],"properties":{"artistname":"Pitbull"}},{"type":"node","id":"1192","labels":["Artist"],"properties":{"artistname":"The Knocks"}},{"type":"node","id":"1193","labels":["Artist"],"properties":{"artistname":"Digga"}},{"type":"node","id":"1194","labels":["Artist"],"properties":{"artistname":"Erik Santos"}},{"type":"node","id":"1195","labels":["Artist"],"properties":{"artistname":"Sheila On 7"}},{"type":"node","id":"1196","labels":["Artist"],"properties":{"artistname":"Del Amitri"}},{"type":"node","id":"1197","labels":["Artist"],"properties":{"artistname":"Nate Dogg"}},{"type":"node","id":"1198","labels":["Artist"],"properties":{"artistname":"Laleh"}},{"type":"node","id":"1199","labels":["Artist"],"properties":{"artistname":"Mike Dunn"}},{"type":"node","id":"1200","labels":["Artist"],"properties":{"artistname":"Arctic Monkeys"}},{"type":"node","id":"1224","labels":["Artist"],"properties":{"artistname":"Susan Egan"}},{"type":"node","id":"1225","labels":["Artist"],"properties":{"artistname":"Theatre Of Tragedy"}},{"type":"node","id":"1226","labels":["Artist"],"properties":{"artistname":"Maná"}},{"type":"node","id":"1227","labels":["Artist"],"properties":{"artistname":"Gilberto Gil"}},{"type":"node","id":"1228","labels":["Artist"],"properties":{"artistname":"Whitney Cummings"}},{"type":"node","id":"1229","labels":["Artist"],"properties":{"artistname":"Mark Kozelek"}},{"type":"node","id":"1230","labels":["Artist"],"properties":{"artistname":"Young-Holt Unlimited"}},{"type":"node","id":"1231","labels":["Artist"],"properties":{"artistname":"Nordic Affect"}},{"type":"node","id":"1232","labels":["Artist"],"properties":{"artistname":"Social Distortion"}},{"type":"node","id":"1233","labels":["Artist"],"properties":{"artistname":"Lenzman"}},{"type":"node","id":"1234","labels":["Artist"],"properties":{"artistname":"Neon Trees"}},{"type":"node","id":"1235","labels":["Artist"],"properties":{"artistname":"Miranda Lambert"}},{"type":"node","id":"1236","labels":["Artist"],"properties":{"artistname":"Janis Martin"}},{"type":"node","id":"1237","labels":["Artist"],"properties":{"artistname":"Stephen Oremus"}},{"type":"node","id":"1238","labels":["Artist"],"properties":{"artistname":"Armin van Buuren"}},{"type":"node","id":"1239","labels":["Artist"],"properties":{"artistname":"Repulsion"}},{"type":"node","id":"1240","labels":["Artist"],"properties":{"artistname":"GO!GO!7188"}},{"type":"node","id":"1241","labels":["Artist"],"properties":{"artistname":"Frankie Knuckles"}},{"type":"node","id":"1242","labels":["Artist"],"properties":{"artistname":"Pantha Du Prince"}},{"type":"node","id":"1243","labels":["Artist"],"properties":{"artistname":"Enya"}},{"type":"node","id":"1244","labels":["Artist"],"properties":{"artistname":"Larry Willis"}},{"type":"node","id":"1245","labels":["Artist"],"properties":{"artistname":"Wolfgang Amadeus Mozart"}},{"type":"node","id":"1246","labels":["Artist"],"properties":{"artistname":"Aimer"}},{"type":"node","id":"1247","labels":["Artist"],"properties":{"artistname":"Nana Caymmi"}},{"type":"node","id":"1248","labels":["Artist"],"properties":{"artistname":"Mini"}},{"type":"node","id":"1249","labels":["Artist"],"properties":{"artistname":"Frank Sinatra"}},{"type":"node","id":"1250","labels":["Artist"],"properties":{"artistname":"Louis Armstrong"}},{"type":"node","id":"1251","labels":["Artist"],"properties":{"artistname":"Israel & New Breed"}},{"type":"node","id":"1252","labels":["Artist"],"properties":{"artistname":"Epica"}},{"type":"node","id":"1253","labels":["Artist"],"properties":{"artistname":"Sean Callery"}},{"type":"node","id":"1254","labels":["Artist"],"properties":{"artistname":"Rusko"}},{"type":"node","id":"1255","labels":["Artist"],"properties":{"artistname":"Stromae"}},{"type":"node","id":"1256","labels":["Artist"],"properties":{"artistname":"Kush"}},{"type":"node","id":"1257","labels":["Artist"],"properties":{"artistname":"Andreya Triana"}},{"type":"node","id":"1258","labels":["Artist"],"properties":{"artistname":"The Emotions"}},{"type":"node","id":"1284","labels":["Artist"],"properties":{"artistname":"Culcha Candela"}},{"type":"node","id":"1285","labels":["Artist"],"properties":{"artistname":"Tycho"}},{"type":"node","id":"1286","labels":["Artist"],"properties":{"artistname":"Rivermaya"}},{"type":"node","id":"1287","labels":["Artist"],"properties":{"artistname":"Adriana Calcanhotto"}},{"type":"node","id":"1288","labels":["Artist"],"properties":{"artistname":"Suffocation"}},{"type":"node","id":"1289","labels":["Artist"],"properties":{"artistname":"Lia"}},{"type":"node","id":"1290","labels":["Artist"],"properties":{"artistname":"Laura Nyro"}},{"type":"node","id":"1291","labels":["Artist"],"properties":{"artistname":"Brian McKnight"}},{"type":"node","id":"1292","labels":["Artist"],"properties":{"artistname":"Jax Jones"}},{"type":"node","id":"1293","labels":["Artist"],"properties":{"artistname":"Franz Schubert"}},{"type":"node","id":"1294","labels":["Artist"],"properties":{"artistname":"Céline Dion"}},{"type":"node","id":"1295","labels":["Artist"],"properties":{"artistname":"Tarkan"}},{"type":"node","id":"1296","labels":["Artist"],"properties":{"artistname":"Demonios Da Garoa"}},{"type":"node","id":"1297","labels":["Artist"],"properties":{"artistname":"Greeicy"}},{"type":"node","id":"1298","labels":["Artist"],"properties":{"artistname":"Jenő Jandó"}},{"type":"node","id":"1299","labels":["Artist"],"properties":{"artistname":"Berry Goodman"}},{"type":"node","id":"1300","labels":["Artist"],"properties":{"artistname":"Josh Gracin"}},{"type":"node","id":"1301","labels":["Artist"],"properties":{"artistname":"Giorgio Conte"}},{"type":"node","id":"1302","labels":["Artist"],"properties":{"artistname":"Anderson .Paak"}},{"type":"node","id":"1303","labels":["Artist"],"properties":{"artistname":"Alan Gilbert"}},{"type":"node","id":"1304","labels":["Artist"],"properties":{"artistname":"Ohashi Trio"}},{"type":"node","id":"1305","labels":["Artist"],"properties":{"artistname":"Rodney Atkins"}},{"type":"node","id":"1306","labels":["Artist"],"properties":{"artistname":"Yonder Mountain String Band"}},{"type":"node","id":"1307","labels":["Artist"],"properties":{"artistname":"Mae"}},{"type":"node","id":"1308","labels":["Artist"],"properties":{"artistname":"k.d. lang"}},{"type":"node","id":"1309","labels":["Artist"],"properties":{"artistname":"Blue"}},{"type":"node","id":"1310","labels":["Artist"],"properties":{"artistname":"Elephant Man"}},{"type":"node","id":"1311","labels":["Artist"],"properties":{"artistname":"Keith Jarrett"}},{"type":"node","id":"1312","labels":["Artist"],"properties":{"artistname":"Jason Mraz"}},{"type":"node","id":"1313","labels":["Artist"],"properties":{"artistname":"The Album Leaf"}},{"type":"node","id":"1333","labels":["Artist"],"properties":{"artistname":"Jack Ü"}},{"type":"node","id":"1334","labels":["Artist"],"properties":{"artistname":"The Middle East"}},{"type":"node","id":"1335","labels":["Artist"],"properties":{"artistname":"Luciano Pavarotti"}},{"type":"node","id":"1336","labels":["Artist"],"properties":{"artistname":"Los Amantes De Lola"}},{"type":"node","id":"1337","labels":["Artist"],"properties":{"artistname":"a-ha"}},{"type":"node","id":"1338","labels":["Artist"],"properties":{"artistname":"Urselle"}},{"type":"node","id":"1339","labels":["Artist"],"properties":{"artistname":"Fatboy Slim"}},{"type":"node","id":"1340","labels":["Artist"],"properties":{"artistname":"Busy Signal"}},{"type":"node","id":"1341","labels":["Artist"],"properties":{"artistname":"Oceanlab"}},{"type":"node","id":"1342","labels":["Artist"],"properties":{"artistname":"Azealia Banks"}},{"type":"node","id":"1343","labels":["Artist"],"properties":{"artistname":"Karametade"}},{"type":"node","id":"1344","labels":["Artist"],"properties":{"artistname":"Forró do Muido"}},{"type":"node","id":"1345","labels":["Artist"],"properties":{"artistname":"Riya"}},{"type":"node","id":"1346","labels":["Artist"],"properties":{"artistname":"Pretty Lights"}},{"type":"node","id":"1347","labels":["Artist"],"properties":{"artistname":"Electric Wizard"}},{"type":"node","id":"1348","labels":["Artist"],"properties":{"artistname":"coldrain"}},{"type":"node","id":"1349","labels":["Artist"],"properties":{"artistname":"Sub Focus"}},{"type":"node","id":"1350","labels":["Artist"],"properties":{"artistname":"Maluma"}},{"type":"node","id":"1351","labels":["Artist"],"properties":{"artistname":"Marilia Medalha"}},{"type":"node","id":"1352","labels":["Artist"],"properties":{"artistname":"Arcangel"}},{"type":"node","id":"1353","labels":["Artist"],"properties":{"artistname":"MOBB"}},{"type":"node","id":"1354","labels":["Artist"],"properties":{"artistname":"Amit Trivedi"}},{"type":"node","id":"1355","labels":["Artist"],"properties":{"artistname":"Mansour"}},{"type":"node","id":"1356","labels":["Artist"],"properties":{"artistname":"Astor Piazzolla"}},{"type":"node","id":"1357","labels":["Artist"],"properties":{"artistname":"Tom Petty and the Heartbreakers"}},{"type":"node","id":"1358","labels":["Artist"],"properties":{"artistname":"alt-J"}},{"type":"node","id":"1359","labels":["Artist"],"properties":{"artistname":"Jason Derulo"}},{"type":"node","id":"1360","labels":["Artist"],"properties":{"artistname":"The Nerves"}},{"type":"node","id":"1361","labels":["Artist"],"properties":{"artistname":"H.E.R."}},{"type":"node","id":"1362","labels":["Artist"],"properties":{"artistname":"Falamansa"}},{"type":"node","id":"1363","labels":["Artist"],"properties":{"artistname":"Joe Henry"}},{"type":"node","id":"1364","labels":["Artist"],"properties":{"artistname":"Joe Hisaishi"}},{"type":"node","id":"1365","labels":["Artist"],"properties":{"artistname":"Aqualung"}},{"type":"node","id":"1366","labels":["Artist"],"properties":{"artistname":"Weezer"}},{"type":"node","id":"1391","labels":["Artist"],"properties":{"artistname":"Kelly Chen"}},{"type":"node","id":"1392","labels":["Artist"],"properties":{"artistname":"Dio"}},{"type":"node","id":"1393","labels":["Artist"],"properties":{"artistname":"Foster The People"}},{"type":"node","id":"1394","labels":["Artist"],"properties":{"artistname":"Ratt"}},{"type":"node","id":"1395","labels":["Artist"],"properties":{"artistname":"Commodores"}},{"type":"node","id":"1396","labels":["Artist"],"properties":{"artistname":"CeCe Rogers"}},{"type":"node","id":"1397","labels":["Artist"],"properties":{"artistname":"Andy Montañez"}},{"type":"node","id":"1398","labels":["Artist"],"properties":{"artistname":"Omega"}},{"type":"node","id":"1399","labels":["Artist"],"properties":{"artistname":"Lil Yachty"}},{"type":"node","id":"1400","labels":["Artist"],"properties":{"artistname":"Solange"}},{"type":"node","id":"1401","labels":["Artist"],"properties":{"artistname":"Tiësto"}},{"type":"node","id":"1402","labels":["Artist"],"properties":{"artistname":"Rionegro & Solimões"}},{"type":"node","id":"1403","labels":["Artist"],"properties":{"artistname":"Clinton Cerejo"}},{"type":"node","id":"1404","labels":["Artist"],"properties":{"artistname":"Lindsey Stirling"}},{"type":"node","id":"1405","labels":["Artist"],"properties":{"artistname":"Foals"}},{"type":"node","id":"1406","labels":["Artist"],"properties":{"artistname":"Vaneese Thomas"}},{"type":"node","id":"1407","labels":["Artist"],"properties":{"artistname":"Solomun"}},{"type":"node","id":"1408","labels":["Artist"],"properties":{"artistname":"Einar Steen-Nøkleberg"}},{"type":"node","id":"1409","labels":["Artist"],"properties":{"artistname":"Ojos de Brujo"}},{"type":"node","id":"1410","labels":["Artist"],"properties":{"artistname":"Alex Fong"}},{"type":"node","id":"1411","labels":["Artist"],"properties":{"artistname":"The Postal Service"}},{"type":"node","id":"1412","labels":["Artist"],"properties":{"artistname":"Frankie Lymon & The Teenagers"}},{"type":"node","id":"1413","labels":["Artist"],"properties":{"artistname":"Itzhak Perlman"}},{"type":"node","id":"1414","labels":["Artist"],"properties":{"artistname":"Kelly Clarkson"}},{"type":"node","id":"1415","labels":["Artist"],"properties":{"artistname":"Ramin Djawadi"}},{"type":"node","id":"1416","labels":["Artist"],"properties":{"artistname":"DeJ Loaf"}},{"type":"node","id":"1417","labels":["Artist"],"properties":{"artistname":"OneRepublic"}},{"type":"node","id":"1433","labels":["Artist"],"properties":{"artistname":"Psycroptic"}},{"type":"node","id":"1434","labels":["Artist"],"properties":{"artistname":"Toadies"}},{"type":"node","id":"1437","labels":["Artist"],"properties":{"artistname":"Macklemore & Ryan Lewis"}},{"type":"node","id":"1438","labels":["Artist"],"properties":{"artistname":"Go, Diego, Go!"}},{"type":"node","id":"1439","labels":["Artist"],"properties":{"artistname":"Jeff Mills"}},{"type":"node","id":"1440","labels":["Artist"],"properties":{"artistname":"Kool & The Gang"}},{"type":"node","id":"1441","labels":["Artist"],"properties":{"artistname":"David Gray"}},{"type":"node","id":"1442","labels":["Artist"],"properties":{"artistname":"Ken Ishii"}},{"type":"node","id":"1443","labels":["Artist"],"properties":{"artistname":"Héctor Lavoe"}},{"type":"node","id":"1444","labels":["Artist"],"properties":{"artistname":"É O Tchan"}},{"type":"node","id":"1445","labels":["Artist"],"properties":{"artistname":"Lifehouse"}},{"type":"node","id":"1446","labels":["Artist"],"properties":{"artistname":"Jack Johnson"}},{"type":"node","id":"1447","labels":["Artist"],"properties":{"artistname":"Music For Little People Choir"}},{"type":"node","id":"1448","labels":["Artist"],"properties":{"artistname":"Justice"}},{"type":"node","id":"1449","labels":["Artist"],"properties":{"artistname":"Kid Rock"}},{"type":"node","id":"1450","labels":["Artist"],"properties":{"artistname":"Gundula Janowitz"}},{"type":"node","id":"1451","labels":["Artist"],"properties":{"artistname":"Laurindo Almeida"}},{"type":"node","id":"1452","labels":["Artist"],"properties":{"artistname":"August Alsina"}},{"type":"node","id":"1453","labels":["Artist"],"properties":{"artistname":"Cybotron"}},{"type":"node","id":"1454","labels":["Artist"],"properties":{"artistname":"Shigeto"}},{"type":"node","id":"1455","labels":["Artist"],"properties":{"artistname":"Ferreck Dawn"}},{"type":"node","id":"1456","labels":["Artist"],"properties":{"artistname":"Henry Purcell"}},{"type":"node","id":"1457","labels":["Artist"],"properties":{"artistname":"Hot Rod Circuit"}},{"type":"node","id":"1458","labels":["Artist"],"properties":{"artistname":"Enslaved"}},{"type":"node","id":"1459","labels":["Artist"],"properties":{"artistname":"Afshin"}},{"type":"node","id":"1460","labels":["Artist"],"properties":{"artistname":"José Gallardo"}},{"type":"node","id":"1461","labels":["Artist"],"properties":{"artistname":"Patrick O'Hearn"}},{"type":"node","id":"1462","labels":["Artist"],"properties":{"artistname":"Green Day"}},{"type":"node","id":"1463","labels":["Artist"],"properties":{"artistname":"Eagle-Eye Cherry"}},{"type":"node","id":"1464","labels":["Artist"],"properties":{"artistname":"Habib Koité"}},{"type":"node","id":"1465","labels":["Artist"],"properties":{"artistname":"Foo Fighters"}},{"type":"node","id":"1466","labels":["Artist"],"properties":{"artistname":"Sandesh Shandilya"}},{"type":"node","id":"1467","labels":["Artist"],"properties":{"artistname":"Nazareth"}},{"type":"node","id":"1480","labels":["Artist"],"properties":{"artistname":"Carlos Santana"}},{"type":"node","id":"1481","labels":["Artist"],"properties":{"artistname":"Misfits"}},{"type":"node","id":"1482","labels":["Artist"],"properties":{"artistname":"Elephant Stone"}},{"type":"node","id":"1483","labels":["Artist"],"properties":{"artistname":"Juan Carlos Casas"}},{"type":"node","id":"1484","labels":["Artist"],"properties":{"artistname":"Bastille"}},{"type":"node","id":"1485","labels":["Artist"],"properties":{"artistname":"Richard Clayderman"}},{"type":"node","id":"1486","labels":["Artist"],"properties":{"artistname":"Buddy Guy"}},{"type":"node","id":"1487","labels":["Artist"],"properties":{"artistname":"enya-sang"}},{"type":"node","id":"1488","labels":["Artist"],"properties":{"artistname":"Zaz"}},{"type":"node","id":"1489","labels":["Artist"],"properties":{"artistname":"Shahid Mallya"}},{"type":"node","id":"1490","labels":["Artist"],"properties":{"artistname":"Savages"}},{"type":"node","id":"1491","labels":["Artist"],"properties":{"artistname":"Aidonia"}},{"type":"node","id":"1492","labels":["Artist"],"properties":{"artistname":"Samba De Raiz"}},{"type":"node","id":"1493","labels":["Artist"],"properties":{"artistname":"Black Eyed Peas"}},{"type":"node","id":"1494","labels":["Artist"],"properties":{"artistname":"Blackmill"}},{"type":"node","id":"1495","labels":["Artist"],"properties":{"artistname":"Flux Pavilion"}},{"type":"node","id":"1496","labels":["Artist"],"properties":{"artistname":"Modest Mouse"}},{"type":"node","id":"1497","labels":["Artist"],"properties":{"artistname":"DJ Khaled"}},{"type":"node","id":"1498","labels":["Artist"],"properties":{"artistname":"Fly Boi Keno"}},{"type":"node","id":"1499","labels":["Artist"],"properties":{"artistname":"Bonobo"}},{"type":"node","id":"1500","labels":["Artist"],"properties":{"artistname":"Red Hot Chili Peppers"}},{"type":"node","id":"1501","labels":["Artist"],"properties":{"artistname":"Martin Garrix"}},{"type":"node","id":"1502","labels":["Artist"],"properties":{"artistname":"Rolando Villazón"}},{"type":"node","id":"1503","labels":["Artist"],"properties":{"artistname":"Radiohead"}},{"type":"node","id":"1504","labels":["Artist"],"properties":{"artistname":"Zubin Mehta"}},{"type":"node","id":"1505","labels":["Artist"],"properties":{"artistname":"Casuarina"}},{"type":"node","id":"1506","labels":["Artist"],"properties":{"artistname":"Craig David"}},{"type":"node","id":"1507","labels":["Artist"],"properties":{"artistname":"Michael Crawford"}},{"type":"node","id":"1508","labels":["Artist"],"properties":{"artistname":"Maurizio"}},{"type":"node","id":"1509","labels":["Artist"],"properties":{"artistname":"MONGOL800"}},{"type":"node","id":"1510","labels":["Artist"],"properties":{"artistname":"6LACK"}},{"type":"node","id":"1524","labels":["Artist"],"properties":{"artistname":"Jennifer Lopez"}},{"type":"node","id":"1525","labels":["Artist"],"properties":{"artistname":"Etta James"}},{"type":"node","id":"1526","labels":["Artist"],"properties":{"artistname":"Stray Cats"}},{"type":"node","id":"1527","labels":["Artist"],"properties":{"artistname":"One Direction"}},{"type":"node","id":"1528","labels":["Artist"],"properties":{"artistname":"Unknown Mortal Orchestra"}},{"type":"node","id":"1529","labels":["Artist"],"properties":{"artistname":"Vicente Fernández"}},{"type":"node","id":"1530","labels":["Artist"],"properties":{"artistname":"Gita Gutawa"}},{"type":"node","id":"1531","labels":["Artist"],"properties":{"artistname":"Heart"}},{"type":"node","id":"1532","labels":["Artist"],"properties":{"artistname":"Idina Menzel"}},{"type":"node","id":"1533","labels":["Artist"],"properties":{"artistname":"Silbermond"}},{"type":"node","id":"1534","labels":["Artist"],"properties":{"artistname":"Dua Lipa"}},{"type":"node","id":"1535","labels":["Artist"],"properties":{"artistname":"Kygo"}},{"type":"node","id":"1536","labels":["Artist"],"properties":{"artistname":"Des'ree"}},{"type":"node","id":"1537","labels":["Artist"],"properties":{"artistname":"Suicidal Tendencies"}},{"type":"node","id":"1538","labels":["Artist"],"properties":{"artistname":"Kansas"}},{"type":"node","id":"1539","labels":["Artist"],"properties":{"artistname":"Elizabeth Harwood"}},{"type":"node","id":"1540","labels":["Artist"],"properties":{"artistname":"Sultan Khan"}},{"type":"node","id":"1541","labels":["Artist"],"properties":{"artistname":"deadmau5"}},{"type":"node","id":"1542","labels":["Artist"],"properties":{"artistname":"Da Tweekaz"}},{"type":"node","id":"1543","labels":["Artist"],"properties":{"artistname":"Velvet Revolver"}},{"type":"node","id":"1544","labels":["Artist"],"properties":{"artistname":"Quintino"}},{"type":"node","id":"1545","labels":["Artist"],"properties":{"artistname":"Chief Keef"}},{"type":"node","id":"1546","labels":["Artist"],"properties":{"artistname":"U2"}},{"type":"node","id":"1547","labels":["Artist"],"properties":{"artistname":"Yo La Tengo"}},{"type":"node","id":"1562","labels":["Artist"],"properties":{"artistname":"Guordan Banks"}},{"type":"node","id":"1563","labels":["Artist"],"properties":{"artistname":"Sandy Lam"}},{"type":"node","id":"1564","labels":["Artist"],"properties":{"artistname":"The Lawrence Arms"}},{"type":"node","id":"1565","labels":["Artist"],"properties":{"artistname":"Deadboy"}},{"type":"node","id":"1566","labels":["Artist"],"properties":{"artistname":"Tim Berg"}},{"type":"node","id":"1567","labels":["Artist"],"properties":{"artistname":"Fred Hammond"}},{"type":"node","id":"1568","labels":["Artist"],"properties":{"artistname":"Ali & Gipp"}},{"type":"node","id":"1569","labels":["Artist"],"properties":{"artistname":"Madness"}},{"type":"node","id":"1570","labels":["Artist"],"properties":{"artistname":"The Fray"}},{"type":"node","id":"1571","labels":["Artist"],"properties":{"artistname":"Zomboy"}},{"type":"node","id":"1572","labels":["Artist"],"properties":{"artistname":"Arash"}},{"type":"node","id":"1573","labels":["Artist"],"properties":{"artistname":"Explosions In The Sky"}},{"type":"node","id":"1574","labels":["Artist"],"properties":{"artistname":"Dick Van Dyke"}},{"type":"node","id":"1575","labels":["Artist"],"properties":{"artistname":"Alpines"}},{"type":"node","id":"1576","labels":["Artist"],"properties":{"artistname":"So Solid Crew"}},{"type":"node","id":"1577","labels":["Artist"],"properties":{"artistname":"Panteon Rococo"}},{"type":"node","id":"1578","labels":["Artist"],"properties":{"artistname":"Fatoumata Diawara"}},{"type":"node","id":"1579","labels":["Artist"],"properties":{"artistname":"The Prophet"}},{"type":"node","id":"1580","labels":["Artist"],"properties":{"artistname":"London Philharmonic Choir"}},{"type":"node","id":"1581","labels":["Artist"],"properties":{"artistname":"Cyndi Wang"}},{"type":"node","id":"1582","labels":["Artist"],"properties":{"artistname":"The Bloody Beetroots"}},{"type":"node","id":"1583","labels":["Artist"],"properties":{"artistname":"Opiuo"}},{"type":"node","id":"1584","labels":["Artist"],"properties":{"artistname":"Sam Fan Thomas"}},{"type":"node","id":"1585","labels":["Artist"],"properties":{"artistname":"M. Ward"}},{"type":"node","id":"1586","labels":["Artist"],"properties":{"artistname":"The Freestylers"}},{"type":"node","id":"1587","labels":["Artist"],"properties":{"artistname":"Alesso"}},{"type":"node","id":"1588","labels":["Artist"],"properties":{"artistname":"Ty Segall"}},{"type":"node","id":"1589","labels":["Artist"],"properties":{"artistname":"ChoLam"}},{"type":"node","id":"1590","labels":["Artist"],"properties":{"artistname":"Mastodon"}},{"type":"node","id":"1611","labels":["Artist"],"properties":{"artistname":"Consuelo Velázquez"}},{"type":"node","id":"1612","labels":["Artist"],"properties":{"artistname":"Beth Orton"}},{"type":"node","id":"1613","labels":["Artist"],"properties":{"artistname":"Ozzy Osbourne"}},{"type":"node","id":"1614","labels":["Artist"],"properties":{"artistname":"Wiener Philharmoniker"}},{"type":"node","id":"1615","labels":["Artist"],"properties":{"artistname":"Goldie"}},{"type":"node","id":"1616","labels":["Artist"],"properties":{"artistname":"Joe Zawinul"}},{"type":"node","id":"1617","labels":["Artist"],"properties":{"artistname":"Max C"}},{"type":"node","id":"1618","labels":["Artist"],"properties":{"artistname":"Trio Forrozão"}},{"type":"node","id":"1619","labels":["Artist"],"properties":{"artistname":"Frances"}},{"type":"node","id":"1620","labels":["Artist"],"properties":{"artistname":"Demetri Martin"}},{"type":"node","id":"1621","labels":["Artist"],"properties":{"artistname":"Deepack"}},{"type":"node","id":"1622","labels":["Artist"],"properties":{"artistname":"Ismaël Lô"}},{"type":"node","id":"1623","labels":["Artist"],"properties":{"artistname":"The Prodigy"}},{"type":"node","id":"1631","labels":["Artist"],"properties":{"artistname":"Marisa Monte"}},{"type":"node","id":"1632","labels":["Artist"],"properties":{"artistname":"Rudimental"}},{"type":"node","id":"1633","labels":["Artist"],"properties":{"artistname":"Nils Frahm"}},{"type":"node","id":"1634","labels":["Artist"],"properties":{"artistname":"Savant"}},{"type":"node","id":"1635","labels":["Artist"],"properties":{"artistname":"John Travolta"}},{"type":"node","id":"1636","labels":["Artist"],"properties":{"artistname":"Maelo Ruiz"}},{"type":"node","id":"1637","labels":["Artist"],"properties":{"artistname":"Callalily"}},{"type":"node","id":"1638","labels":["Artist"],"properties":{"artistname":"Snow Patrol"}},{"type":"node","id":"1639","labels":["Artist"],"properties":{"artistname":"Pantera"}},{"type":"node","id":"1640","labels":["Artist"],"properties":{"artistname":"Volbeat"}},{"type":"node","id":"1641","labels":["Artist"],"properties":{"artistname":"Underground Resistance"}},{"type":"node","id":"1642","labels":["Artist"],"properties":{"artistname":"Max Herre"}},{"type":"node","id":"1643","labels":["Artist"],"properties":{"artistname":"Herbert Grönemeyer"}},{"type":"node","id":"1644","labels":["Artist"],"properties":{"artistname":"Motörhead"}},{"type":"node","id":"1645","labels":["Artist"],"properties":{"artistname":"Solar Fields"}},{"type":"node","id":"1646","labels":["Artist"],"properties":{"artistname":"The Get Up Kids"}},{"type":"node","id":"1647","labels":["Artist"],"properties":{"artistname":"Frontliner"}},{"type":"node","id":"1648","labels":["Artist"],"properties":{"artistname":"Phish"}},{"type":"node","id":"1649","labels":["Artist"],"properties":{"artistname":"Nile Rodgers"}},{"type":"node","id":"1650","labels":["Artist"],"properties":{"artistname":"Downlink"}},{"type":"node","id":"1651","labels":["Artist"],"properties":{"artistname":"Panic! At The Disco"}},{"type":"node","id":"1652","labels":["Artist"],"properties":{"artistname":"Alexandra Stan"}},{"type":"node","id":"1653","labels":["Artist"],"properties":{"artistname":"Bob Sinclar"}},{"type":"node","id":"1654","labels":["Artist"],"properties":{"artistname":"Georges Prêtre"}},{"type":"node","id":"1655","labels":["Artist"],"properties":{"artistname":"Chris Thile"}},{"type":"node","id":"1656","labels":["Artist"],"properties":{"artistname":"Shawn Phillips"}},{"type":"node","id":"1657","labels":["Artist"],"properties":{"artistname":"Peter, Paul and Mary"}},{"type":"node","id":"1658","labels":["Artist"],"properties":{"artistname":"Haddaway"}},{"type":"node","id":"1659","labels":["Artist"],"properties":{"artistname":"Nami Tamaki"}},{"type":"node","id":"1660","labels":["Artist"],"properties":{"artistname":"HAIM"}},{"type":"node","id":"1675","labels":["Artist"],"properties":{"artistname":"The Warlocks"}},{"type":"node","id":"1676","labels":["Artist"],"properties":{"artistname":"Memphis May Fire"}},{"type":"node","id":"1677","labels":["Artist"],"properties":{"artistname":"W&W"}},{"type":"node","id":"1678","labels":["Artist"],"properties":{"artistname":"Ken Stringfellow"}},{"type":"node","id":"1679","labels":["Artist"],"properties":{"artistname":"Willie Colón"}},{"type":"node","id":"1680","labels":["Artist"],"properties":{"artistname":"Twisted Sister"}},{"type":"node","id":"1681","labels":["Artist"],"properties":{"artistname":"Conjunto Clasico / Tito Nieves"}},{"type":"node","id":"1682","labels":["Artist"],"properties":{"artistname":"Iamsu!"}},{"type":"node","id":"1683","labels":["Artist"],"properties":{"artistname":"Antônio Carlos Jobim"}},{"type":"node","id":"1684","labels":["Artist"],"properties":{"artistname":"The Backyardigans"}},{"type":"node","id":"1685","labels":["Artist"],"properties":{"artistname":"Paige"}},{"type":"node","id":"1686","labels":["Artist"],"properties":{"artistname":"note native"}},{"type":"node","id":"1687","labels":["Artist"],"properties":{"artistname":"John Coltrane"}},{"type":"node","id":"1688","labels":["Artist"],"properties":{"artistname":"Mother Love Bone"}},{"type":"node","id":"1689","labels":["Artist"],"properties":{"artistname":"Mirei Toyama"}},{"type":"node","id":"1690","labels":["Artist"],"properties":{"artistname":"Osvaldo Pugliese"}},{"type":"node","id":"1691","labels":["Artist"],"properties":{"artistname":"Asking Alexandria"}},{"type":"node","id":"1692","labels":["Artist"],"properties":{"artistname":"Art Popular"}},{"type":"node","id":"1693","labels":["Artist"],"properties":{"artistname":"Hadise"}},{"type":"node","id":"1694","labels":["Artist"],"properties":{"artistname":"Sir Sly"}},{"type":"node","id":"1695","labels":["Artist"],"properties":{"artistname":"Ray Charles"}},{"type":"node","id":"1696","labels":["Artist"],"properties":{"artistname":"Manian"}},{"type":"node","id":"1697","labels":["Artist"],"properties":{"artistname":"Dorothy Little Happy"}},{"type":"node","id":"1698","labels":["Artist"],"properties":{"artistname":"DJ Kentaro"}},{"type":"node","id":"1699","labels":["Artist"],"properties":{"artistname":"Raamlaxman"}},{"type":"node","id":"1700","labels":["Artist"],"properties":{"artistname":"Paul van Dyk"}},{"type":"node","id":"1701","labels":["Artist"],"properties":{"artistname":"Michael Ray"}},{"type":"node","id":"1702","labels":["Artist"],"properties":{"artistname":"Bee Gees"}},{"type":"node","id":"1703","labels":["Artist"],"properties":{"artistname":"Freaks"}},{"type":"node","id":"1704","labels":["Artist"],"properties":{"artistname":"Death From Above 1979"}},{"type":"node","id":"1705","labels":["Artist"],"properties":{"artistname":"Darude"}},{"type":"node","id":"1706","labels":["Artist"],"properties":{"artistname":"Justin Bieber"}},{"type":"node","id":"1707","labels":["Artist"],"properties":{"artistname":"BOOTS"}},{"type":"node","id":"1708","labels":["Artist"],"properties":{"artistname":"Björn Skifs"}},{"type":"node","id":"1709","labels":["Artist"],"properties":{"artistname":"George Jones"}},{"type":"node","id":"1710","labels":["Artist"],"properties":{"artistname":"Bill Monroe & His Blue Grass Boys"}},{"type":"node","id":"1724","labels":["Artist"],"properties":{"artistname":"Calibre 50"}},{"type":"node","id":"1725","labels":["Artist"],"properties":{"artistname":"Morbid Angel"}},{"type":"node","id":"1726","labels":["Artist"],"properties":{"artistname":"Proyecto Uno"}},{"type":"node","id":"1727","labels":["Artist"],"properties":{"artistname":"Yo-Yo Ma"}},{"type":"node","id":"1728","labels":["Artist"],"properties":{"artistname":"Peter Bjorn and John"}},{"type":"node","id":"1729","labels":["Artist"],"properties":{"artistname":"DJ Dex"}},{"type":"node","id":"1730","labels":["Artist"],"properties":{"artistname":"The Pietasters"}},{"type":"node","id":"1731","labels":["Artist"],"properties":{"artistname":"Evil Nine"}},{"type":"node","id":"1732","labels":["Artist"],"properties":{"artistname":"Justin Nozuka"}},{"type":"node","id":"1733","labels":["Artist"],"properties":{"artistname":"Psyko Punkz"}},{"type":"node","id":"1734","labels":["Artist"],"properties":{"artistname":"Adonis"}},{"type":"node","id":"1735","labels":["Artist"],"properties":{"artistname":"Alex Somers"}},{"type":"node","id":"1736","labels":["Artist"],"properties":{"artistname":"Banda Magníficos"}},{"type":"node","id":"1737","labels":["Artist"],"properties":{"artistname":"Geoff Zanelli"}},{"type":"node","id":"1738","labels":["Artist"],"properties":{"artistname":"Miley Cyrus"}},{"type":"node","id":"1739","labels":["Artist"],"properties":{"artistname":"Bengü"}},{"type":"node","id":"1740","labels":["Artist"],"properties":{"artistname":"George Baker Selection"}},{"type":"node","id":"1741","labels":["Artist"],"properties":{"artistname":"BiS"}},{"type":"node","id":"1742","labels":["Artist"],"properties":{"artistname":"Metrik"}},{"type":"node","id":"1743","labels":["Artist"],"properties":{"artistname":"Fleetwood Mac"}},{"type":"node","id":"1744","labels":["Artist"],"properties":{"artistname":"Minor Threat"}},{"type":"node","id":"1745","labels":["Artist"],"properties":{"artistname":"Pique Novo"}},{"type":"node","id":"1746","labels":["Artist"],"properties":{"artistname":"Sean Paul"}},{"type":"node","id":"1747","labels":["Artist"],"properties":{"artistname":"Shankar Mahadevan"}},{"type":"node","id":"1748","labels":["Artist"],"properties":{"artistname":"Dempagumi.Inc"}},{"type":"node","id":"1749","labels":["Artist"],"properties":{"artistname":"Caroline O'Connor"}},{"type":"node","id":"1750","labels":["Artist"],"properties":{"artistname":"Lynx "}},{"type":"node","id":"1751","labels":["Artist"],"properties":{"artistname":"Jeff Buckley"}},{"type":"node","id":"1752","labels":["Artist"],"properties":{"artistname":"Alkilados"}},{"type":"node","id":"1753","labels":["Artist"],"properties":{"artistname":"Rise Against"}},{"type":"node","id":"1754","labels":["Artist"],"properties":{"artistname":"Augustus Pablo"}},{"type":"node","id":"1755","labels":["Artist"],"properties":{"artistname":"Alan Silvestri"}},{"type":"node","id":"1773","labels":["Artist"],"properties":{"artistname":"Téo & Edu"}},{"type":"node","id":"1774","labels":["Artist"],"properties":{"artistname":"Beatriz Luengo"}},{"type":"node","id":"1775","labels":["Artist"],"properties":{"artistname":"Jane's Addiction"}},{"type":"node","id":"1776","labels":["Artist"],"properties":{"artistname":"Lenine"}},{"type":"node","id":"1777","labels":["Artist"],"properties":{"artistname":"Blak Ryno"}},{"type":"node","id":"1778","labels":["Artist"],"properties":{"artistname":"Galaxy 2 Galaxy"}},{"type":"node","id":"1779","labels":["Artist"],"properties":{"artistname":"Mount Dreams"}},{"type":"node","id":"1780","labels":["Artist"],"properties":{"artistname":"Jeremy Olander"}},{"type":"node","id":"1781","labels":["Artist"],"properties":{"artistname":"Thåström"}},{"type":"node","id":"1782","labels":["Artist"],"properties":{"artistname":"Alka Yagnik"}},{"type":"node","id":"1783","labels":["Artist"],"properties":{"artistname":"Liquid"}},{"type":"node","id":"1784","labels":["Artist"],"properties":{"artistname":"Miles Davis"}},{"type":"node","id":"1785","labels":["Artist"],"properties":{"artistname":"Michael Jackson"}},{"type":"node","id":"1786","labels":["Artist"],"properties":{"artistname":"Westernhagen"}},{"type":"node","id":"1787","labels":["Artist"],"properties":{"artistname":"Toploader"}},{"type":"node","id":"1788","labels":["Artist"],"properties":{"artistname":"Imagine Dragons"}},{"type":"node","id":"1789","labels":["Artist"],"properties":{"artistname":"Ekamatra"}},{"type":"node","id":"1790","labels":["Artist"],"properties":{"artistname":"Cardi B"}},{"type":"node","id":"1791","labels":["Artist"],"properties":{"artistname":"Isabel Lippitz"}},{"type":"node","id":"1792","labels":["Artist"],"properties":{"artistname":"Sheryl Crow"}},{"type":"node","id":"1793","labels":["Artist"],"properties":{"artistname":"Sam Cooke"}},{"type":"node","id":"1794","labels":["Artist"],"properties":{"artistname":"Ed Sheeran"}},{"type":"node","id":"1795","labels":["Artist"],"properties":{"artistname":"The Charlie Daniels Band"}},{"type":"node","id":"1796","labels":["Artist"],"properties":{"artistname":"李壽全"}},{"type":"node","id":"1797","labels":["Artist"],"properties":{"artistname":"Pickin' On Series"}},{"type":"node","id":"1798","labels":["Artist"],"properties":{"artistname":"Madeon"}},{"type":"node","id":"1799","labels":["Artist"],"properties":{"artistname":"Tig Notaro"}},{"type":"node","id":"1800","labels":["Artist"],"properties":{"artistname":"Andy & Kouros"}},{"type":"node","id":"1801","labels":["Artist"],"properties":{"artistname":"amazarashi"}},{"type":"node","id":"1802","labels":["Artist"],"properties":{"artistname":"Mad Caddies"}},{"type":"node","id":"1812","labels":["Artist"],"properties":{"artistname":"2000 And One"}},{"type":"node","id":"2833","labels":["Artist"],"properties":{"artistname":"BoB"}},{"type":"node","id":"2834","labels":["Artist"],"properties":{"artistname":"John P Kee"}},{"type":"node","id":"2835","labels":["Artist"],"properties":{"artistname":"Lebo M"}},{"type":"node","id":"2836","labels":["Artist"],"properties":{"artistname":"St Lucia"}},{"type":"node","id":"28147","labels":["Artist"],"properties":{"artistname":"K Michelle"}},{"type":"node","id":"28148","labels":["Artist"],"properties":{"artistname":"K S Chithra"}},{"type":"node","id":"39079","labels":["Artist"],"properties":{"artistname":"Ms Lauryn Hill"}},{"type":"node","id":"39080","labels":["Artist"],"properties":{"artistname":"Mr Fingers"}},{"type":"node","id":"39081","labels":["Artist"],"properties":{"artistname":"Charlie Brown Jr"}},{"type":"node","id":"39082","labels":["Artist"],"properties":{"artistname":"illgates"}},{"type":"node","id":"50060","labels":["Artist"],"properties":{"artistname":"Anderson Paak"}},{"type":"node","id":"50061","labels":["Artist"],"properties":{"artistname":"kd lang"}},{"type":"node","id":"50062","labels":["Artist"],"properties":{"artistname":"The  Leaf"}},{"type":"node","id":"50063","labels":["Artist"],"properties":{"artistname":"HER"}},{"type":"node","id":"61029","labels":["Artist"],"properties":{"artistname":"Go"}},{"type":"node","id":"61030","labels":["Artist"],"properties":{"artistname":"Diego"}},{"type":"node","id":"61031","labels":["Artist"],"properties":{"artistname":"Go!"}},{"type":"node","id":"61032","labels":["Artist"],"properties":{"artistname":"M Ward"}},{"type":"node","id":"71649","labels":["Artist"],"properties":{"artistname":"Peter"}},{"type":"node","id":"71650","labels":["Artist"],"properties":{"artistname":"Paul and Mary"}},{"type":"node","id":"71651","labels":["Artist"],"properties":{"artistname":"DempagumiInc"}}]}